Metadata-Version: 2.1
Name: yman
Version: 1.0.0
Summary: Yakuake session management
Home-page: https://github.com/szymex73/yman
Author: szymex73
Author-email: szymex73@gmail.com
License: MIT
Platform: UNKNOWN
Requires-Python: >=3.7
License-File: LICENSE
